{"total":544,"engines":{"boa":462,"jsc":0,"jsc_exp":0,"kiesel":472,"libjs":147,"nova":0,"porffor":6,"qjs":0,"qjs_ng":0,"sm":544,"sm_exp":544,"v8":542,"v8_exp":542},"files":{"intl402/Temporal/ZonedDateTime/canonicalize-calendar.js":{"total":1,"engines":{"boa":0,"jsc":0,"jsc_exp":0,"kiesel":0,"libjs":0,"nova":0,"porffor":0,"qjs":0,"qjs_ng":0,"sm":1,"sm_exp":1,"v8":1,"v8_exp":1}},"intl402/Temporal/ZonedDateTime/compare":{"total":5,"engines":{"boa":5,"jsc":0,"jsc_exp":0,"kiesel":5,"libjs":4,"nova":0,"porffor":0,"qjs":0,"qjs_ng":0,"sm":5,"sm_exp":5,"v8":5,"v8_exp":5}},"intl402/Temporal/ZonedDateTime/construct-non-utc-non-iso.js":{"total":1,"engines":{"boa":1,"jsc":0,"jsc_exp":0,"kiesel":1,"libjs":0,"nova":0,"porffor":0,"qjs":0,"qjs_ng":0,"sm":1,"sm_exp":1,"v8":1,"v8_exp":1}},"intl402/Temporal/ZonedDateTime/etc-timezone.js":{"total":1,"engines":{"boa":1,"jsc":0,"jsc_exp":0,"kiesel":1,"libjs":0,"nova":0,"porffor":0,"qjs":0,"qjs_ng":0,"sm":1,"sm_exp":1,"v8":1,"v8_exp":1}},"intl402/Temporal/ZonedDateTime/from":{"total":36,"engines":{"boa":32,"jsc":0,"jsc_exp":0,"kiesel":35,"libjs":8,"nova":0,"porffor":5,"qjs":0,"qjs_ng":0,"sm":36,"sm_exp":36,"v8":36,"v8_exp":36}},"intl402/Temporal/ZonedDateTime/iana-legacy-names.js":{"total":1,"engines":{"boa":1,"jsc":0,"jsc_exp":0,"kiesel":1,"libjs":0,"nova":0,"porffor":0,"qjs":0,"qjs_ng":0,"sm":1,"sm_exp":1,"v8":1,"v8_exp":1}},"intl402/Temporal/ZonedDateTime/legacy-non-iana.js":{"total":1,"engines":{"boa":1,"jsc":0,"jsc_exp":0,"kiesel":1,"libjs":0,"nova":0,"porffor":1,"qjs":0,"qjs_ng":0,"sm":1,"sm_exp":1,"v8":1,"v8_exp":1}},"intl402/Temporal/ZonedDateTime/links-backward.js":{"total":1,"engines":{"boa":1,"jsc":0,"jsc_exp":0,"kiesel":1,"libjs":0,"nova":0,"porffor":0,"qjs":0,"qjs_ng":0,"sm":1,"sm_exp":1,"v8":1,"v8_exp":1}},"intl402/Temporal/ZonedDateTime/links-backzone.js":{"total":1,"engines":{"boa":1,"jsc":0,"jsc_exp":0,"kiesel":1,"libjs":1,"nova":0,"porffor":0,"qjs":0,"qjs_ng":0,"sm":1,"sm_exp":1,"v8":1,"v8_exp":1}},"intl402/Temporal/ZonedDateTime/links-etcetera.js":{"total":1,"engines":{"boa":1,"jsc":0,"jsc_exp":0,"kiesel":1,"libjs":0,"nova":0,"porffor":0,"qjs":0,"qjs_ng":0,"sm":1,"sm_exp":1,"v8":1,"v8_exp":1}},"intl402/Temporal/ZonedDateTime/links.js":{"total":1,"engines":{"boa":0,"jsc":0,"jsc_exp":0,"kiesel":0,"libjs":0,"nova":0,"porffor":0,"qjs":0,"qjs_ng":0,"sm":1,"sm_exp":1,"v8":1,"v8_exp":1}},"intl402/Temporal/ZonedDateTime/non-canonical-utc.js":{"total":1,"engines":{"boa":1,"jsc":0,"jsc_exp":0,"kiesel":1,"libjs":0,"nova":0,"porffor":0,"qjs":0,"qjs_ng":0,"sm":1,"sm_exp":1,"v8":1,"v8_exp":1}},"intl402/Temporal/ZonedDateTime/prototype":{"total":490,"engines":{"boa":416,"jsc":0,"jsc_exp":0,"kiesel":421,"libjs":133,"nova":0,"porffor":0,"qjs":0,"qjs_ng":0,"sm":490,"sm_exp":490,"v8":488,"v8_exp":488}},"intl402/Temporal/ZonedDateTime/supported-values-of.js":{"total":1,"engines":{"boa":0,"jsc":0,"jsc_exp":0,"kiesel":1,"libjs":0,"nova":0,"porffor":0,"qjs":0,"qjs_ng":0,"sm":1,"sm_exp":1,"v8":1,"v8_exp":1}},"intl402/Temporal/ZonedDateTime/timezone-case-insensitive.js":{"total":1,"engines":{"boa":0,"jsc":0,"jsc_exp":0,"kiesel":1,"libjs":0,"nova":0,"porffor":0,"qjs":0,"qjs_ng":0,"sm":1,"sm_exp":1,"v8":1,"v8_exp":1}},"intl402/Temporal/ZonedDateTime/timezone-ids-basic.js":{"total":1,"engines":{"boa":1,"jsc":0,"jsc_exp":0,"kiesel":1,"libjs":1,"nova":0,"porffor":0,"qjs":0,"qjs_ng":0,"sm":1,"sm_exp":1,"v8":1,"v8_exp":1}}}}